src/__init__.py
src/alphasort.py
alphasort-0.1.21.dist-info/LICENSE
alphasort-0.1.21.dist-info/METADATA
alphasort-0.1.21.dist-info/WHEEL
alphasort-0.1.21.dist-info/entry_points.txt
alphasort-0.1.21.dist-info/RECORD
