Metadata-Version: 2.1
Name: alphasort
Version: 0.1.21
Summary: Sort lines within regions of a file.
License: LICENSE
Author: Josiah Coad
Author-email: josiah@coad.net
Requires-Python: >=3.13,<4.0
Classifier: License :: Other/Proprietary License
Classifier: Programming Language :: Python :: 3
Classifier: Programming Language :: Python :: 3.13
Requires-Dist: argcomplete (>=3.5.2,<4.0.0)
Requires-Dist: requests (>=2.32.3,<3.0.0)
Requires-Dist: tomli (>=2.2.1,<3.0.0)
